{
  "pile1": {
    "nom": "pile1",
    "description": "woooooooooooooooooooooooooooooooooooooooooooooooooooooooooooooooooooooooooooooooooooooooooooooooooooooooooooooooooooooooooooooow",
    "cartes": [
      {
        "id": 1,
        "question": "question1",
        "reponse": "reponse1"
      },
      {
        "id": 2,
        "question": "question2",
        "reponse": "reponse1"
      },
      {
        "id": 3,
        "question": "question3",
        "reponse": "reponse1"
      }
    ],
    "stats": {
      "cartesJouees": 0,
      "cartesTrouvees": 0,
      "cartesNonTrouvees": 0,
      "cartesParMinutes": 0.0,
      "tempsPasse": 0.0
    }
  },
  "nouvelle pile n° 5": {
    "nom": "nouvelle pile n° 5",
    "description": "no description",
    "cartes": [],
    "stats": {
      "cartesJouees": 0,
      "cartesTrouvees": 0,
      "cartesNonTrouvees": 0,
      "cartesParMinutes": 0.0,
      "tempsPasse": 0.0
    }
  },
  "nouvelle pile n° 4": {
    "nom": "nouvelle pile n° 4",
    "description": "no description",
    "cartes": [],
    "stats": {
      "cartesJouees": 0,
      "cartesTrouvees": 0,
      "cartesNonTrouvees": 0,
      "cartesParMinutes": 0.0,
      "tempsPasse": 0.0
    }
  },
  "nouvelle pile n° 3": {
    "nom": "nouvelle pile n° 3",
    "description": "no description",
    "cartes": [],
    "stats": {
      "cartesJouees": 0,
      "cartesTrouvees": 0,
      "cartesNonTrouvees": 0,
      "cartesParMinutes": 0.0,
      "tempsPasse": 0.0
    }
  },
  "nouvelle pile n° 2": {
    "nom": "nouvelle pile n° 2",
    "description": "no description",
    "cartes": [],
    "stats": {
      "cartesJouees": 0,
      "cartesTrouvees": 0,
      "cartesNonTrouvees": 0,
      "cartesParMinutes": 0.0,
      "tempsPasse": 0.0
    }
  },
  "pile2": {
    "nom": "pile2",
    "description": "description pile 2",
    "cartes": [
      {
        "id": 1,
        "question": "question1",
        "reponse": "reponse1"
      },
      {
        "id": 2,
        "question": "question2",
        "reponse": "reponse1"
      },
      {
        "id": 3,
        "question": "question3",
        "reponse": "reponse1"
      }
    ],
    "stats": {
      "cartesJouees": 0,
      "cartesTrouvees": 0,
      "cartesNonTrouvees": 0,
      "cartesParMinutes": 0.0,
      "tempsPasse": 0.0
    }
  }
}